amazondata/__init__.py
amazondata/product_details_extractor.py
amazondata/search_result_extractor.py
amazondata-0.1.2.dist-info/LICENSE.txt
amazondata-0.1.2.dist-info/METADATA
amazondata-0.1.2.dist-info/WHEEL
amazondata-0.1.2.dist-info/top_level.txt
amazondata-0.1.2.dist-info/RECORD
