Metadata-Version: 2.1
Name: amazondata
Version: 0.1.2
Summary: A python package to get amazon product and search data in json form. The package does not require any API keys as it works by scraping the amazon page.
Home-page: https://github.com/AnupKumarPanwar/amazondata
Download-URL: https://pypi.org/project/amazondata/
Author: Anup Kumar Panwar
Author-email: 1anuppanwar@gmail.com
License: MIT
Keywords: Amazon,Scraper
License-File: LICENSE.txt
Requires-Dist: selectorlib
Requires-Dist: requests
